[{"input": "\u5357\u7f8e\u6817\u9f20", "output": "\u8d6b"}, {"input": "\u70ed\u95f9", "output": "\u6211"}, {"input": "\u865a\u5f31\u7684", "output": "\u548c"}, {"input": "\u89e3\u51b3", "output": "\u8fd9"}, {"input": "\u70e4\u7bb1", "output": "V"}, {"input": "\u6709\u624d\u534e\u7684", "output": "\u4e00\u4e2a"}, {"input": "\u76f8\u4fe1", "output": "\u548c"}, {"input": "\u4eb2\u5c5e", "output": "\u6211"}, {"input": "\u9ed1\u7329\u7329", "output": "\u8d6b"}, {"input": "\u7fbd\u6bdb", "output": "\u548c"}, {"input": "\u7f9a\u7f8a", "output": "R"}, {"input": "\u660e\u4eae\u7684", "output": "R"}, {"input": "\u5976\u725b", "output": "\u8fd9"}, {"input": "\u5de8\u5634\u9e1f", "output": "\u8fd9"}, {"input": "\u6b23\u559c\u82e5\u72c2", "output": "\u78b3"}, {"input": "\u5173\u4e8e", "output": "\u4e59"}, {"input": "\u5bb3\u6015", "output": "\u548c"}, {"input": "\u732b\u9f2c", "output": "\u548c"}, {"input": "\u53c9", "output": "\u8fd9"}, {"input": "\u65c5\u884c", "output": "R"}, {"input": "\u5feb\u901f\u5730", "output": "\u4e00\u4e2a"}, {"input": "\u7c89\u8272\u7684", "output": "\u6211"}, {"input": "\u53ef\u89c6\u5316", "output": "\u6211"}, {"input": "\u8001\u9f20", "output": "\u8fd9"}, {"input": "\u6ce8\u610f", "output": "\u8fd9"}, {"input": "\u72f8", "output": "\u4e00\u4e2a"}, {"input": "\u51b0\u5c4b", "output": "\u683c"}, {"input": "\u684c\u5b50", "output": "\u4e00\u4e2a"}, {"input": "\u806a\u660e\u7684", "output": "\u7c73"}, {"input": "\u671f\u95f4", "output": "\u5728"}, {"input": "\u52c7\u6562\u7684", "output": "R"}, {"input": "\u80e1\u841d\u535c", "output": "\u4e00\u4e2a"}, {"input": "\u957f\u7684", "output": "\u8fd9"}, {"input": "\u83e0\u841d", "output": "\u6211"}, {"input": "\u575a\u5b9a\u4e0d\u79fb", "output": "\u5426"}, {"input": "\u80c6\u5c0f", "output": "\u8fd9"}, {"input": "\u4e4b\u95f4", "output": "\u548c"}, {"input": "\u9a7c\u9e7f", "output": "\u8fd9"}, {"input": "\u8c08\u5224", "output": "\u548c"}, {"input": "\u5b81\u9759", "output": "R"}, {"input": "\u548c\u853c\u53ef\u4eb2", "output": "F"}, {"input": "\u590d\u5236", "output": "\u8fd9"}, {"input": "\u6a58\u5b50", "output": "\u4e00\u4e2a"}, {"input": "\u5339\u914d", "output": "\u4e00\u4e2a"}, {"input": "\u5d07\u62dc", "output": "\u5fb7"}, {"input": "\u9c7c", "output": "\u6211"}, {"input": "\u8df3", "output": "\u5728"}, {"input": "\u4f5c\u4e3a", "output": "\u6211"}, {"input": "\u725b\u8089", "output": "\u548c"}, {"input": "\u69b4\u83b2", "output": "\u5728"}, {"input": "\u5e74\u8f7b\u7684", "output": "\u8fd9"}, {"input": "\u8d8a\u6a58", "output": "\u5728"}, {"input": "\u5b9a\u4e49", "output": "\u548c"}, {"input": "\u9999", "output": "\u5426"}, {"input": "\u53ef\u9760\u7684", "output": "\u548c"}, {"input": "\u4f1e", "output": "\u7c73"}, {"input": "\u6000\u7591", "output": "\u8fd9"}, {"input": "\u5584\u826f", "output": "\u6211"}, {"input": "\u6572", "output": "\u5426"}, {"input": "\u58f6", "output": "\u548c"}, {"input": "\u6dd8\u6c14", "output": "\u4e00\u4e2a"}, {"input": "\u6fb3\u6d32\u91ce\u72d7", "output": "\u6211"}, {"input": "\u6e29\u548c\u7684", "output": "\u548c"}, {"input": "\u79c3\u9e6b", "output": "\u5728"}, {"input": "\u718a\u732b", "output": "\u4e00\u4e2a"}, {"input": "\u66f4\u65b0", "output": "\u78f7"}, {"input": "\u8003\u8651", "output": "\u8fd9"}, {"input": "\u9760\u8fd1", "output": "\u548c"}, {"input": "\u54b8", "output": "\u4e00\u4e2a"}, {"input": "\u9e2d\u5b50", "output": "\u5728"}, {"input": "\u9700\u8981", "output": "\u548c"}, {"input": "\u901a\u8fc7", "output": "\u8d6b"}, {"input": "\u8c79", "output": "\u548c"}, {"input": "\u7535\u89c6", "output": "\u548c"}, {"input": "\u8986\u76c6\u5b50", "output": "\u4e00\u4e2a"}, {"input": "\u660e\u667a\u7684", "output": "\u6211"}, {"input": "\u6e38\u8247", "output": "\u4e00\u4e2a"}, {"input": "\u70c2", "output": "\u8fd9"}, {"input": "\u91ce\u725b", "output": "\u6211"}, {"input": "\u732b", "output": "\u4e00\u4e2a"}, {"input": "\u4fdd\u6301", "output": "\u548c"}, {"input": "\u64cd\u7eb5", "output": "\u4e00\u4e2a"}, {"input": "\u7ed9", "output": "\u6211"}, {"input": "\u978b", "output": "\u8d6b"}, {"input": "\u86c7", "output": "\u5426"}, {"input": "\u9009\u62e9", "output": "\u8d6b"}, {"input": "\u6cb9\u6843", "output": "\u548c"}, {"input": "\u7a9d", "output": "\u8fd9"}, {"input": "\u7bee\u5b50", "output": "\u4e00\u4e2a"}, {"input": "\u7315\u7334\u6843", "output": "\u6211"}, {"input": "\u877e", "output": "\u4e00\u4e2a"}, {"input": "\u773c\u955c\u86c7", "output": "\u8fd9"}, {"input": "\u4e50\u89c2", "output": "\u78f7"}, {"input": "\u5f3a\u608d", "output": "\u5426"}, {"input": "\u9e70", "output": "\u4e00\u4e2a"}, {"input": "\u86fe", "output": "\u8fd9"}, {"input": "\u76ae\u8247", "output": "\u4e00\u4e2a"}, {"input": "\u5706\u5f62\u7684", "output": "\u8fd9"}, {"input": "\u6bdb\u866b", "output": "\u4e00\u4e2a"}, {"input": "\u521b\u9020", "output": "R"}, {"input": "\u4fe1\u5c01", "output": "\u5426"}, {"input": "\u4ed3\u9f20", "output": "\u4e00\u4e2a"}, {"input": "\u67ff\u5b50", "output": "\u548c"}, {"input": "\u95e8", "output": "\u8fd9"}, {"input": "\u7ba1\u7406", "output": "\u4e00\u4e2a"}, {"input": "\u4ec1\u6148", "output": "\u548c"}, {"input": "\u8d62", "output": "\u6211"}, {"input": "\u66f2\u5947\u997c", "output": "\u8fd9"}, {"input": "\u6d3b\u6cfc", "output": "\u6211"}, {"input": "\u52c7\u6562", "output": "\u8fd9"}, {"input": "\u6bef\u5b50", "output": "\u5927\u53f7"}, {"input": "\u86cb", "output": "\u683c"}, {"input": "\u61d2\u60f0", "output": "\u5927\u53f7"}, {"input": "\u7f8e\u6d32\u72ee", "output": "\u8fd9"}, {"input": "\u638c\u63e1", "output": "\u4e00\u4e2a"}, {"input": "\u5e78\u8fd0\u7684", "output": "\u5728"}, {"input": "\u770b\u6cd5", "output": "\u6211"}, {"input": "\u611a\u8822\u7684", "output": "\u7535\u89c6"}, {"input": "\u873b\u8713", "output": "R"}, {"input": "\u9a74", "output": "\u8fd9"}, {"input": "\u6709\u5f39\u6027\u7684", "output": "\u548c"}, {"input": "\u77ed\u7684", "output": "\u8d6b"}, {"input": "\u8ba1\u7b97", "output": "\u4e00\u4e2a"}, {"input": "\u5c3d\u7ba1", "output": "\u548c"}, {"input": "\u94a5\u5319", "output": "\u548c"}, {"input": "\u73a9", "output": "\u5927\u53f7"}, {"input": "\u5927\u58f0", "output": "\u8fd9"}, {"input": "\u5927\u80c6", "output": "\u4e00\u4e2a"}, {"input": "\u751f\u4ea7", "output": "R"}, {"input": "\u6469\u6258\u8f66", "output": "\u8fd9"}, {"input": "\u9ca8\u9c7c", "output": "\u8d6b"}, {"input": "\u6536\u96c6", "output": "\u8fd9"}, {"input": "\u975b\u9752", "output": "\u5426"}, {"input": "\u9009\u62e9", "output": "\u548c"}, {"input": "\u4e89\u8bba", "output": "R"}, {"input": "\u559c\u6b22", "output": "\u6211"}, {"input": "\u7834\u574f", "output": "\u548c"}, {"input": "\u8bf4\u8bdd", "output": "\u78f7"}, {"input": "\u74f6\u5b50", "output": "\u8fd9"}, {"input": "\u9493\u9c7c\u7aff", "output": "\u6211"}, {"input": "\u79cd\u65cf", "output": "\u4e00\u4e2a"}, {"input": "\u8513\u8d8a\u8393", "output": "R"}, {"input": "\u90ca\u72fc", "output": "\u8fd9"}, {"input": "\u8bb0\u4f4f", "output": "\u548c"}, {"input": "\u9a6f\u9e7f", "output": "\u548c"}, {"input": "\u6e34", "output": "\u8d6b"}, {"input": "\u5206\u6790", "output": "\u5426"}, {"input": "\u9762\u98df", "output": "\u4e00\u4e2a"}, {"input": "\u82f9\u679c", "output": "\u78f7"}, {"input": "\u52a8\u6001\u7684", "output": "\u548c"}, {"input": "\u9b23\u8725", "output": "\u683c"}, {"input": "\u5976\u6cb9", "output": "R"}, {"input": "\u674e\u5b50", "output": "\u5927\u53f7"}, {"input": "\u6d77\u8c61", "output": "\u4e00\u4e2a"}, {"input": "\u7cbe\u529b\u5145\u6c9b", "output": "\u5426"}, {"input": "\u5c24\u514b\u91cc\u91cc\u7434", "output": "\u94be"}, {"input": "\u8815\u866b", "output": "\u8fd9"}, {"input": "\u91ce\u5c71\u7f8a", "output": "\u4e59"}, {"input": "\u737e", "output": "\u4e00\u4e2a"}, {"input": "\u73bb\u7483", "output": "\u5927\u53f7"}, {"input": "\u601d\u8003", "output": "\u8d6b"}, {"input": "\u53cd\u6620", "output": "\u548c"}, {"input": "\u70db\u53f0", "output": "\u4e00\u4e2a"}, {"input": "\u654f\u9510\u7684", "output": "\u548c"}, {"input": "\u670d\u52a1", "output": "\u548c"}, {"input": "\u539f\u8c05", "output": "\u8fd9"}, {"input": "\u6d77\u9cd7", "output": "\u8fd9"}, {"input": "\u7bee\u7403", "output": "\u4e00\u4e2a"}, {"input": "\u5411\u4e0a", "output": "\u78f7"}, {"input": "\u6a44\u6984", "output": "\u5927\u53f7"}, {"input": "\u516c\u732a", "output": "\u8fd9"}, {"input": "\u9f50\u67cf\u6797\u98de\u8247", "output": "\u548c"}, {"input": "\u6d17\u624b\u95f4", "output": "\u8fd9"}, {"input": "\u51b7\u9759\u7684", "output": "\u4e00\u4e2a"}, {"input": "\u6728\u7434", "output": "\u548c"}, {"input": "\u8d85\u8fc7", "output": "V"}, {"input": "\u8c7a", "output": "\u4e00\u4e2a"}, {"input": "\u53d1\u5149\u7684", "output": "\u5728"}, {"input": "\u5927\u80c6\u7684", "output": "\u8fd9"}, {"input": "\u9e35\u9e1f", "output": "\u5e74\u4ee3"}, {"input": "\u80e1\u6912", "output": "\u548c"}, {"input": "\u94c3\u9f13", "output": "\u4e00\u4e2a"}, {"input": "\u7535\u8bdd", "output": "\u8d6b"}, {"input": "\u68a8", "output": "\u548c"}, {"input": "\u8fc7\u53bb\u7684", "output": "\u4e00\u4e2a"}, {"input": "\u6cb3\u9a6c", "output": "\u6211"}, {"input": "\u4e25\u8083\u7684", "output": "\u548c"}, {"input": "\u9e3d\u5b50", "output": "\u6211"}, {"input": "\u677e\u9f20", "output": "\u95ee"}, {"input": "\u806a\u660e\u7684", "output": "\u5927\u53f7"}, {"input": "\u4eb2\u5207", "output": "R"}, {"input": "\u7b11", "output": "\u4e00\u4e2a"}, {"input": "\u5927\u7684", "output": "\u6211"}, {"input": "\u4f46", "output": "\u5728"}, {"input": "\u526a\u5200", "output": "\u78b3"}, {"input": "\u95ee\u9898", "output": "\u5728"}, {"input": "\u9ec4\u8272\u7684", "output": "\u548c"}, {"input": "\u98de\u6da8", "output": "\u8fd9"}, {"input": "\u6f14\u8bb2", "output": "\u548c"}, {"input": "\u6709", "output": "\u4e00\u4e2a"}, {"input": "\u56e0\u4e3a", "output": "\u8fd9"}, {"input": "\u7280\u725b", "output": "\u8d6b"}, {"input": "\u767d\u8272\u7684", "output": "\u8d6b"}, {"input": "\u5e06", "output": "\u4e00\u4e2a"}, {"input": "\u5b54\u96c0", "output": "\u548c"}, {"input": "\u7684", "output": "F"}, {"input": "\u5996\u5a06", "output": "\u5426"}, {"input": "\u77e5\u8bc6\u6e0a\u535a", "output": "\u5426"}, {"input": "\u540a\u5e8a", "output": "\u4e00\u4e2a"}, {"input": "\u8718\u86db", "output": "\u78f7"}, {"input": "\u5ca9\u77f3", "output": "\u8fd9"}, {"input": "\u9ed1\u8393", "output": "\u5927\u53f7"}, {"input": "\u5154\u5b50", "output": "\u4e00\u4e2a"}, {"input": "\u56de\u65cb\u9556", "output": "\u8fd9"}, {"input": "\u4ee5\u4e0b", "output": "\u548c"}, {"input": "\u5b9e\u8df5", "output": "R"}, {"input": "\u7d2b\u8272", "output": "\u6211"}, {"input": "\u8ff7\u4eba", "output": "\u8d6b"}, {"input": "\u9cc4\u9c7c", "output": "R"}, {"input": "\u8774\u8776", "output": "\u5728"}, {"input": "\u610f\u8bc6\u5230", "output": "\u548c"}, {"input": "\u5b58\u5728", "output": "\u5341"}, {"input": "\u8282\u7701", "output": "\u4e00\u4e2a"}, {"input": "\u4e0b", "output": "\u5426"}, {"input": "\u897f\u74dc", "output": "\u4e00\u4e2a"}, {"input": "\u9f20", "output": "\u4e00\u4e2a"}, {"input": "\u62c9\u94fe", "output": "\u6211"}, {"input": "\u9a6f\u9e7f", "output": "\u4e00\u4e2a"}, {"input": "\u9f9f", "output": "\u5728"}, {"input": "\u8fdb\u5165", "output": "\u5426"}, {"input": "\u9f99\u867e", "output": "\u8fd9"}, {"input": "\u9f13", "output": "R"}, {"input": "\u5c71\u7f8a", "output": "\u8fd9"}, {"input": "\u82b1\u6817\u9f20", "output": "\u8d6b"}, {"input": "\u7ade\u4e89", "output": "\u8fd9"}, {"input": "\u9e45", "output": "\u8fd9"}, {"input": "\u505a\u4e00\u4e2a\u9985\u997c", "output": "\u4e00\u4e2a"}, {"input": "\u6295\u6807", "output": "\u548c"}, {"input": "\u6a31\u6843", "output": "\u8d6b"}, {"input": "\u9ec4\u9f20\u72fc", "output": "\u548c"}, {"input": "\u6d77\u8c79", "output": "\u548c"}, {"input": "\u8003\u62c9", "output": "\u8fd9"}, {"input": "\u951a", "output": "\u5426"}, {"input": "\u4ef7\u503c", "output": "\u4e00\u4e2a"}, {"input": "\u4e3a\u4e86", "output": "\u8fd9"}, {"input": "\u653b\u51fb", "output": "\u7535\u89c6"}, {"input": "\u9a6c\u62c9\u5361\u65af", "output": "\u4e00\u4e2a"}, {"input": "\u4f7f\u7528", "output": "\u5e74\u4ee3"}, {"input": "\u590d\u5370", "output": "\u548c"}, {"input": "\u5f02\u60f3\u5929\u5f00", "output": "\u8d6b"}, {"input": "\u57f9\u80b2", "output": "\u5728"}, {"input": "\u5c65\u884c", "output": "\u548c"}, {"input": "\u6e7f\u7684", "output": "\u548c"}, {"input": "\u9a86\u9a7c", "output": "\u4e00\u4e2a"}, {"input": "\u9879\u94fe", "output": "\u548c"}, {"input": "\u524d", "output": "\u548c"}, {"input": "\u89c2\u5bdf", "output": "\u4e59"}, {"input": "\u6700\u5927\u5316", "output": "\u4e00\u4e2a"}, {"input": "\u5927\u9ec4\u8702", "output": "\u8fd9"}, {"input": "\u7a7a\u7684", "output": "\u4e00\u4e2a"}, {"input": "\u7eff\u8272\u7684", "output": "R"}, {"input": "\u6c34\u8c5a", "output": "\u4e00\u4e2a"}, {"input": "\u7eb8", "output": "\u4e00\u4e2a"}, {"input": "\u7cbe\u7f8e\u7684", "output": "\u5341"}, {"input": "\u8b66\u62a5", "output": "\u5927\u53f7"}, {"input": "\u5230", "output": "\u5426"}, {"input": "\u81ed\u9f2c", "output": "\u94be"}, {"input": "\u6cb9\u70b8\u5708\u997c", "output": "\u8fd9"}, {"input": "\u67d1\u6a58", "output": "\u5927\u53f7"}, {"input": "\u8bfb", "output": "\u548c"}, {"input": "\u6728\u74dc", "output": "\u4e00\u4e2a"}, {"input": "\u5409\u4ed6", "output": "\u5728"}, {"input": "\u6247\u5b50", "output": "\u4e00\u4e2a"}, {"input": "\u9e66\u9e49", "output": "\u4e00\u4e2a"}, {"input": "\u67d4\u8f6f\u7684", "output": "\u8fd9"}, {"input": "\u5feb\u4e50\u7684", "output": "\u4e00\u4e2a"}, {"input": "\u9ad8\u7684", "output": "\u4e00\u4e2a"}, {"input": "\u4e0b\u8dea", "output": "\u5426"}, {"input": "\u9ed1\u8272\u7684", "output": "\u5927\u53f7"}, {"input": "\u5728\u54ea\u91cc", "output": "\u8fd9"}, {"input": "\u7cd6\u679c", "output": "\u4e00\u4e2a"}, {"input": "\u7f9a\u7f8a", "output": "\u4e00\u4e2a"}, {"input": "\u53ef\u7231\u7684", "output": "\u8fd9"}, {"input": "\u624e\u666e", "output": "\u4e00\u4e2a"}, {"input": "\u641c\u7d22", "output": "\u548c"}, {"input": "\u9cc4\u9c7c", "output": "\u5927\u53f7"}, {"input": "\u548c\u8c10", "output": "\u4e00\u4e2a"}, {"input": "\u732a", "output": "\u6211"}, {"input": "\u63a2\u7d22", "output": "\u5341"}, {"input": "\u65e5\u671f", "output": "\u4e00\u4e2a"}, {"input": "\u9a6c", "output": "\u8fd9"}, {"input": "\u53e4\u602a\u7684", "output": "\u5728"}, {"input": "\u96d5\u5851", "output": "\u78b3"}, {"input": "\u624b\u8868", "output": "R"}, {"input": "\u81ea\u884c\u8f66", "output": "\u6211"}, {"input": "\u6e05\u767d\u7684", "output": "\u5426"}, {"input": "\u75c5\u4eba", "output": "\u4e00\u4e2a"}, {"input": "\u82e6\u7684", "output": "\u6211"}, {"input": "\u574f\u7684", "output": "\u4e00\u4e2a"}, {"input": "\u70ed\u5fc3", "output": "\u4e00\u4e2a"}, {"input": "\u51b3\u5b9a", "output": "\u548c"}, {"input": "\u73a9\u6742\u800d", "output": "\u5728"}, {"input": "\u4f01\u9e45", "output": "\u548c"}, {"input": "\u91cd\u7684", "output": "\u548c"}, {"input": "\u673a\u667a", "output": "\u6211"}, {"input": "\u84dd\u8272\u7684", "output": "\u5927\u53f7"}, {"input": "\u8c1c", "output": "\u5728"}, {"input": "\u70ed\u60c5\u7684", "output": "\u4e00\u4e2a"}, {"input": "\u5730\u56fe", "output": "\u4e00\u4e2a"}, {"input": "\u5173\u6000", "output": "\u4e00\u4e2a"}, {"input": "\u6807\u8bb0", "output": "\u4e00\u4e2a"}, {"input": "\u7ecf\u8fc7", "output": "\u548c"}, {"input": "\u7ec4\u7ec7", "output": "R"}, {"input": "\u8ff7\u4eba", "output": "\u4e00\u4e2a"}, {"input": "\u8292\u679c", "output": "\u4e00\u4e2a"}, {"input": "\u730e\u8c79", "output": "\u8d6b"}, {"input": "\u8d1f\u9f20", "output": "\u78f7"}, {"input": "\u7b11", "output": "\u4e00\u4e2a"}, {"input": "\u4eb2\u70ed", "output": "F"}, {"input": "\u4e09\u6587\u9c7c", "output": "\u4e00\u4e2a"}, {"input": "\u8003\u8651", "output": "\u8fd9"}, {"input": "\u6807\u8bb0", "output": "\u4e00\u4e2a"}, {"input": "\u539a\u7684", "output": "\u8d6b"}, {"input": "\u7f51\u7403\u62cd", "output": "\u548c"}, {"input": "\u7406\u89e3", "output": "\u5426"}, {"input": "\u9178\u5976", "output": "\u8fd9"}, {"input": "\u542c\u5230", "output": "\u548c"}, {"input": "\u5411\u5f80", "output": "\u548c"}, {"input": "\u56fe\u7247", "output": "\u6211"}, {"input": "\u87b3\u8782", "output": "\u4e00\u4e2a"}, {"input": "\u886c\u886b", "output": "\u8d6b"}, {"input": "\u79bb\u5f00", "output": "F"}, {"input": "\u5fe0\u5b9e", "output": "\u4e00\u4e2a"}, {"input": "\u6e9c\u6e9c\u7403", "output": "\u8fd9"}, {"input": "\u70ed\u7684", "output": "\u8fd9"}, {"input": "\u81ea\u7136\u7684", "output": "\u4e00\u4e2a"}, {"input": "\u72ec\u7279\u7684", "output": "\u5426"}, {"input": "\u65e0\u79c1", "output": "\u5426"}, {"input": "\u736d", "output": "\u7535\u89c6"}, {"input": "\u8d85\u8fc7", "output": "\u548c"}, {"input": "\u5149\u8292\u56db\u5c04", "output": "\u4e00\u4e2a"}, {"input": "\u88ab\u5b50", "output": "\u5728"}, {"input": "\u624b\u5957", "output": "\u5927\u53f7"}, {"input": "\u82cf\u6253", "output": "\u8fd9"}, {"input": "\u52fa\u5b50", "output": "\u78f7"}, {"input": "\u83b7\u5f97", "output": "\u4e59"}, {"input": "\u753b\u67b6", "output": "\u4e00\u4e2a"}, {"input": "\u55b7\u6cc9", "output": "\u8fd9"}, {"input": "\u9012\u9001", "output": "\u548c"}, {"input": "\u660e\u667a\u7684", "output": "\u548c"}, {"input": "\u91cd\u70b9", "output": "\u8fd9"}, {"input": "\u756a\u8304", "output": "\u8fd9"}, {"input": "\u53d1\u5c55", "output": "\u548c"}, {"input": "\u51f6\u731b\u7684", "output": "\u6211"}, {"input": "\u7334", "output": "\u8fd9"}, {"input": "\u8001\u864e", "output": "\u6211"}, {"input": "\u706b\u8f66", "output": "R"}, {"input": "\u98de\u673a", "output": "\u6211"}, {"input": "\u611a\u8822\u7684", "output": "\u6211"}, {"input": "\u7acb\u65b9\u4f53", "output": "\u5728"}, {"input": "\u4e50\u89c2\u7684", "output": "\u78f7"}, {"input": "\u654f\u6377", "output": "\u683c"}, {"input": "\u6c41", "output": "\u5728"}, {"input": "\u5927\u7329\u7329", "output": "\u8fd9"}, {"input": "\u955c\u5b50", "output": "\u6211"}, {"input": "\u83b4\u82e3", "output": "\u548c"}, {"input": "\u8bc1\u660e\u5408\u6cd5", "output": "\u5728"}, {"input": "\u53ef\u7231\u7684", "output": "\u5fb7"}, {"input": "\u6c89\u601d", "output": "\u548c"}, {"input": "\u5728", "output": "\u7535\u89c6"}, {"input": "\u514b\u670d", "output": "V"}, {"input": "\u9ad8\u8d35", "output": "\u8fd9"}, {"input": "\u5b66\u4e60", "output": "\u548c"}, {"input": "\u7c73", "output": "\u6211"}, {"input": "\u9e45\u6bdb\u7b14", "output": "\u5728"}, {"input": "\u5e72\u51c0\u7684", "output": "\u5927\u53f7"}, {"input": "\u9488\u7ec7", "output": "\u5426"}, {"input": "\u5feb\u7684", "output": "\u5728"}, {"input": "\u63b8\u5b50", "output": "\u5728"}, {"input": "\u9e8b\u9e7f", "output": "\u5927\u53f7"}, {"input": "\u5efa\u9020", "output": "\u5728"}, {"input": "\u73ca\u745a", "output": "\u8fd9"}, {"input": "\u77e5\u9053", "output": "\u5426"}, {"input": "\u5c45\u4f4f", "output": "\u6211"}, {"input": "\u6b65\u67aa", "output": "\u6211"}, {"input": "\u6e34\u671b\u7684", "output": "\u4e00\u4e2a"}, {"input": "\u5927\u7ea6", "output": "R"}, {"input": "\u770b", "output": "\u6211"}, {"input": "\u8ba8\u8bba", "output": "\u6211"}, {"input": "\u949f", "output": "\u5927\u53f7"}, {"input": "\u6765\u7535", "output": "\u5927\u53f7"}, {"input": "\u5feb\u4e50", "output": "\u8fd9"}, {"input": "\u7403", "output": "\u4e00\u4e2a"}, {"input": "\u653e\u677e", "output": "\u548c"}, {"input": "\u8f9b\u8fa3\u7684", "output": "\u78f7"}, {"input": "\u8ba2\u4e66\u673a", "output": "\u7535\u89c6"}, {"input": "\u7f8a", "output": "\u8d6b"}, {"input": "\u81ea\u59cb\u81f3\u7ec8", "output": "\u8d6b"}, {"input": "\u58a8\u6c34", "output": "\u5426"}, {"input": "\u81ea\u4ece", "output": "\u6211"}, {"input": "\u65fa\u76db", "output": "\u5341"}, {"input": "\u7ea2\u8272\u7684", "output": "\u548c"}, {"input": "\u5b8c\u5168\u7684", "output": "\u8fd9"}, {"input": "\u67da\u5b50", "output": "R"}, {"input": "\u4e00", "output": "\u4e00\u4e2a"}, {"input": "\u53ef\u4eb2", "output": "\u7c73"}, {"input": "\u6253\u5f00", "output": "\u78f7"}, {"input": "\u96ea\u8c82", "output": "\u548c"}, {"input": "\u7eb1", "output": "\u4e00\u4e2a"}, {"input": "\u53cb\u597d\u7684", "output": "R"}, {"input": "\u72d0\u7334", "output": "\u548c"}, {"input": "\u8bbe\u8ba1", "output": "\u548c"}, {"input": "\u684c\u5b50", "output": "\u548c"}, {"input": "\u4ed9\u4eba\u638c", "output": "\u4e00\u4e2a"}, {"input": "\u87d1\u8782", "output": "\u8fd9"}, {"input": "\u4e4b\u5185", "output": "\u6211"}, {"input": "\u6392\u7403", "output": "\u8fd9"}, {"input": "\u8001\u7684", "output": "\u5927\u53f7"}, {"input": "\u5939\u514b", "output": "\u4e00\u4e2a"}, {"input": "\u8019", "output": "\u4e00\u4e2a"}, {"input": "\u542c", "output": "\u6211"}, {"input": "\u9ed1\u6591\u7f9a", "output": "\u7c73"}, {"input": "\u4fee\u526a", "output": "R"}, {"input": "\u91d1\u521a\u9e66\u9e49", "output": "\u4e00\u4e2a"}, {"input": "\u4f24\u5fc3", "output": "\u4e00\u4e2a"}, {"input": "\u9e48", "output": "\u548c"}, {"input": "\u7f8a\u9a7c", "output": "\u5927\u53f7"}, {"input": "\u523a\u732c", "output": "\u548c"}, {"input": "\u8bc1\u5b9e", "output": "\u4e00\u4e2a"}, {"input": "\u4e4c\u9e26", "output": "R"}, {"input": "\u6bd4\u8428", "output": "\u6211"}, {"input": "x \u5c04\u7ebf", "output": "-"}, {"input": "\u5305", "output": "\u4e00\u4e2a"}, {"input": "\u5728", "output": "\u5426"}, {"input": "\u53d1\u5237", "output": "\u4e00\u4e2a"}, {"input": "\u571f\u5730", "output": "\u4e00\u4e2a"}, {"input": "\u591a\u4e8e", "output": "\u4e59"}, {"input": "\u6d77\u8707", "output": "\u548c"}, {"input": "\u5728\u540e\u9762", "output": "\u548c"}, {"input": "\u571f\u8c46", "output": "\u8fd9"}, {"input": "\u5145\u6ee1\u5e0c\u671b", "output": "\u8fd9"}, {"input": "\u72d2\u72d2", "output": "\u4e00\u4e2a"}, {"input": "\u624b\u98ce\u7434", "output": "\u78b3"}, {"input": "\u7591\u60d1\u7684", "output": "\u5728"}, {"input": "\u7b14\u8bb0\u672c", "output": "\u8fd9"}, {"input": "\u96be\u7684", "output": "\u4e00\u4e2a"}, {"input": "\u6795\u5934", "output": "\u6211"}, {"input": "\u88d9\u5b50", "output": "R"}, {"input": "\u918b\u6817", "output": "\u8fd9"}, {"input": "\u5e74\u8f7b\u7684", "output": "\u8fd9"}, {"input": "\u9b45\u529b\u975e\u51e1", "output": "\u8d6b"}, {"input": "\u7ed3\u675f", "output": "\u6211"}, {"input": "\u91cc\u9762", "output": "\u5426"}, {"input": "\u68af\u5b50", "output": "\u4e00\u4e2a"}, {"input": "\u6536\u97f3\u673a", "output": "\u4e00\u4e2a"}, {"input": "\u8f6c\u6362", "output": "R"}, {"input": "\u6d77\u725b", "output": "\u4e00\u4e2a"}, {"input": "\u5728", "output": "\u5426"}, {"input": "\u6bdb\u5dfe", "output": "\u8fd9"}, {"input": "\u9ea6\u514b\u98ce", "output": "\u6211"}, {"input": "\u673a\u667a", "output": "\u5728"}, {"input": "\u6709\u5173", "output": "\u8fd9"}, {"input": "\u624b\u8868", "output": "\u4e00\u4e2a"}, {"input": "\u540e", "output": "F"}, {"input": "\u7f8e\u6d32\u8c79", "output": "\u5728"}, {"input": "\u7545\u5feb", "output": "\u4e00\u4e2a"}, {"input": "\u671d\u5411", "output": "\u8fd9"}, {"input": "\u722c", "output": "\u5927\u53f7"}, {"input": "\u4e0d\u559c\u6b22", "output": "\u6211"}, {"input": "\u7266\u725b", "output": "\u4e00\u4e2a"}, {"input": "\u6559", "output": "\u548c"}, {"input": "\u889c\u5b50", "output": "\u8fd9"}, {"input": "\u72fc", "output": "\u8fd9"}, {"input": "\u53d1\u5e03", "output": "\u548c"}, {"input": "\u8424\u706b\u866b", "output": "\u6211"}, {"input": "\u65c1", "output": "\u548c"}, {"input": "\u9187\u539a", "output": "\u548c"}, {"input": "\u871c\u8702", "output": "\u548c"}, {"input": "\u8fbe\u5230", "output": "\u78b3"}, {"input": "\u58ee\u4e3d", "output": "\u4e00\u4e2a"}, {"input": "\u77f3\u69b4", "output": "\u8fd9"}, {"input": "\u5c0f\u63d0\u7434", "output": "\u6211"}, {"input": "\u4ee4\u4eba\u6109\u5feb\u7684", "output": "\u683c"}, {"input": "\u5236\u4f5c", "output": "\u4e00\u4e2a"}, {"input": "\u5982\u56fe", "output": "\u6211"}, {"input": "\u9965\u997f\u7684", "output": "\u5728"}, {"input": "\u8db3\u667a\u591a\u8c0b", "output": "\u548c"}, {"input": "\u6d77\u8c5a", "output": "\u8fd9"}, {"input": "\u65b0\u7684", "output": "\u548c"}, {"input": "\u4e4b\u4e2d", "output": "\u7c73"}, {"input": "\u79d1\u83ab\u591a", "output": "\u8fd9"}, {"input": "\u5f3a\u7684", "output": "\u7535\u89c6"}, {"input": "\u897f\u756a\u83b2", "output": "\u4e00\u4e2a"}, {"input": "\u6807\u7b7e", "output": "\u4e00\u4e2a"}, {"input": "\u8d77\u91cd\u673a", "output": "R"}, {"input": "\u901a\u6c14\u7ba1", "output": "\u5426"}, {"input": "\u5544\u6728\u9e1f", "output": "\u8fd9"}, {"input": "\u706b\u9f99\u679c", "output": "R"}, {"input": "\u5b66\u4e60", "output": "\u7535\u89c6"}, {"input": "\u6cd5\u5b98", "output": "\u5728"}, {"input": "\u5904\u7406", "output": "\u4e00\u4e2a"}, {"input": "\u5feb\u6d3b\u5730", "output": "\u8fd9"}, {"input": "\u6d4b\u8bd5", "output": "\u548c"}, {"input": "\u79cd\u7c7b", "output": "\u6211"}, {"input": "\u52a0\u5165", "output": "\u8fd9"}, {"input": "\u5c71\u9b48", "output": "\u4e00\u4e2a"}, {"input": "\u9b23\u72d7", "output": "\u548c"}, {"input": "\u725b\u7f9a", "output": "\u5426"}, {"input": "\u62b5\u8fbe", "output": "\u548c"}, {"input": "\u5212\u5206", "output": "\u6211"}, {"input": "\u8d44\u683c", "output": "\u5728"}, {"input": "\u6c99\u53d1", "output": "\u8fd9"}, {"input": "\u6d88\u9664", "output": "\u548c"}, {"input": "\u6837\u672c", "output": "\u4e00\u4e2a"}, {"input": "\u849c", "output": "\u4e00\u4e2a"}, {"input": "\u6740", "output": "\u6211"}, {"input": "\u6109\u5feb", "output": "\u548c"}, {"input": "\u54ed", "output": "R"}, {"input": "\u5feb\u6d3b\u7684", "output": "\u8fd9"}, {"input": "\u6b22\u4e50\u7684", "output": "\u6211"}, {"input": "\u771f\u7684", "output": "\u548c"}, {"input": "\u62db\u52df", "output": "\u548c"}, {"input": "\u6602\u8d35\u7684", "output": "\u5341"}, {"input": "\u6709\u8da3\u7684", "output": "\u5728"}, {"input": "\u96c4\u8fa9", "output": "\u5927\u53f7"}, {"input": "\u53c2\u52a0", "output": "\u4e00\u4e2a"}, {"input": "\u80ae\u810f\u7684", "output": "\u6211"}, {"input": "\u72b0\u72f3", "output": "R"}, {"input": "\u6905\u5b50", "output": "\u8d6b"}, {"input": "\u8c79\u732b", "output": "\u78b3"}, {"input": "\u5468\u5230", "output": "\u8d6b"}, {"input": "\u7231", "output": "\u8fd9"}, {"input": "\u7a97\u6237", "output": "\u6211"}, {"input": "\u5229\u4ed6\u4e3b\u4e49", "output": "\u5927\u53f7"}, {"input": "\u706f\u7b3c", "output": "\u4e00\u4e2a"}, {"input": "\u8783\u87f9", "output": "R"}, {"input": "\u7535\u8111", "output": "\u8fd9"}, {"input": "\u5927\u8c61", "output": "\u5927\u53f7"}, {"input": "\u94a2\u7434", "output": "\u6211"}, {"input": "\u5230\u8fbe", "output": "R"}, {"input": "\u51c6\u5907", "output": "R"}, {"input": "\u76f4\u89c9\u7684", "output": "\u5426"}, {"input": "\u82b1\u74f6", "output": "\u4e00\u4e2a"}, {"input": "\u7f50", "output": "\u4e00\u4e2a"}, {"input": "\u65b0\u9c9c\u7684", "output": "R"}, {"input": "\u5c71\u732b", "output": "\u548c"}, {"input": "\u559c\u5e86", "output": "\u5728"}, {"input": "\u76ee\u6807", "output": "\u4e00\u4e2a"}, {"input": "\u9cd7\u9c7c", "output": "\u548c"}, {"input": "\u9e1f", "output": "\u6211"}, {"input": "\u5145\u6ee1\u6d3b\u529b", "output": "\u6211"}, {"input": "\u54e8", "output": "\u8d6b"}, {"input": "\u8bf4\u670d", "output": "\u548c"}, {"input": "\u9e38", "output": "\u7c73"}, {"input": "\u753b\u7b14", "output": "\u4e00\u4e2a"}, {"input": "\u76d8\u5b50", "output": "\u5927\u53f7"}, {"input": "\u5c1d\u8bd5", "output": "R"}, {"input": "\u5200", "output": "\u5426"}, {"input": "\u773c\u955c", "output": "\u5927\u53f7"}, {"input": "\u6a61\u76ae", "output": "R"}, {"input": "\u4ece", "output": "R"}, {"input": "\u82ad\u8549", "output": "\u5927\u53f7"}, {"input": "\u987d\u5f3a", "output": "\u548c"}, {"input": "\u68c0\u67e5", "output": "\u5341"}, {"input": "\u5584\u4e8e\u89c2\u5bdf", "output": "\u4e59"}, {"input": "\u6e29\u6696\u7684", "output": "\u4e00\u4e2a"}, {"input": "\u970d\u52a0\u72d3", "output": "\u94be"}, {"input": "\u5feb\u4e50", "output": "\u8d6b"}, {"input": "\u6709\u521b\u9020\u529b\u7684", "output": "\u5426"}, {"input": "\u654f\u611f\u7684", "output": "\u548c"}, {"input": "\u73b0\u4ee3\u7684", "output": "\u8fd9"}, {"input": "\u6700\u5c0f\u5316", "output": "\u6211"}, {"input": "\u4eab\u53d7", "output": "\u5426"}, {"input": "\u7897", "output": "\u8fd9"}, {"input": "\u54d1\u94c3", "output": "\u5728"}, {"input": "\u8c79", "output": "\u4e00\u4e2a"}, {"input": "\u751f\u957f", "output": "R"}, {"input": "\u5411\u4e0b", "output": "\u8fd9"}, {"input": "\u5e2e\u52a9", "output": "\u548c"}, {"input": "\u5149", "output": "\u6211"}, {"input": "\u91d1\u5b50", "output": "\u8fd9"}, {"input": "\u6539\u53d8", "output": "\u8d6b"}, {"input": "\u888b\u9f20", "output": "\u4e00\u4e2a"}, {"input": "\u957f\u9888\u9e7f", "output": "\u6211"}, {"input": "\u4ea4\u6362", "output": "\u5341"}, {"input": "\u821e\u8e48", "output": "\u4e00\u4e2a"}, {"input": "\u82b1", "output": "\u5927\u53f7"}, {"input": "\u7070\u718a", "output": "R"}, {"input": "\u8bda\u5b9e\u7684", "output": "\u8fd9"}, {"input": "\u5916\u90e8", "output": "\u5728"}, {"input": "\u8ba1\u5212", "output": "\u5927\u53f7"}, {"input": "\u5b89\u9759\u7684", "output": "\u5728"}, {"input": "\u70ed\u60c5\u7684", "output": "\u5426"}, {"input": "\u690d\u7269", "output": "\u5927\u53f7"}, {"input": "\u8721\u70db", "output": "\u4e00\u4e2a"}, {"input": "\u67d1\u6a58", "output": "\u4e00\u4e2a"}, {"input": "\u7ed8\u753b", "output": "\u4e00\u4e2a"}, {"input": "\u57f9\u80b2", "output": "\u5728"}, {"input": "\u6838\u5b9e", "output": "\u548c"}, {"input": "\u571f\u8c5a", "output": "\u4e00\u4e2a"}, {"input": "\u897f\u846b\u82a6", "output": "\u5728"}, {"input": "\u9ab0\u5b50", "output": "\u6211"}, {"input": "\u9178\u6a59", "output": "\u6211"}, {"input": "\u5154\u5b50", "output": "\u5728"}, {"input": "\u5929\u9e45", "output": "\u5728"}, {"input": "\u7329\u7329", "output": "R"}, {"input": "\u58c1\u864e", "output": "\u548c"}, {"input": "\u4fbf\u5b9c\u7684", "output": "\u8d6b"}, {"input": "\u6ca1\u6709", "output": "\u6211"}, {"input": "\u8bbf\u95ee", "output": "\u6211"}, {"input": "\u6177\u6168\u7684", "output": "\u548c"}, {"input": "\u64cd\u4f5c", "output": "\u78f7"}, {"input": "\u6591\u9a6c", "output": "\u548c"}, {"input": "\u7b14\u8bb0\u672c\u7535\u8111", "output": "\u4e00\u4e2a"}, {"input": "\u547c\u5438", "output": "R"}, {"input": "\u51b3\u5b9a", "output": "\u548c"}, {"input": "\u623f\u5b50", "output": "\u8fd9"}, {"input": "\u5de7\u514b\u529b", "output": "\u8d6b"}, {"input": "\u756a\u77f3\u69b4", "output": "\u5728"}, {"input": "\u8717\u725b", "output": "\u5426"}, {"input": "\u706b\u9e21", "output": "\u5728"}, {"input": "\u63ed\u9732", "output": "\u5426"}, {"input": "\u504f\u50fb\u7684", "output": "\u548c"}, {"input": "\u597d\u7684", "output": "\u8fd9"}, {"input": "\u9cb8", "output": "\u8d6b"}, {"input": "\u7ae0\u9c7c", "output": "\u78b3"}, {"input": "\u5230", "output": "\u8fd9"}, {"input": "\u91d1\u521a\u72fc", "output": "\u8fd9"}, {"input": "\u8e22", "output": "\u6211"}, {"input": "\u4f18\u7f8e", "output": "R"}, {"input": "\u56e2\u7ed3", "output": "\u5426"}, {"input": "\u6597\u4e89", "output": "\u6211"}, {"input": "\u62fc\u56fe", "output": "\u6211"}, {"input": "\u806a\u660e\u7684", "output": "\u5426"}, {"input": "\u6ed1\u7a3d\u7684", "output": "\u4e00\u4e2a"}, {"input": "\u76d1\u7763", "output": "V"}, {"input": "\u68ad\u9c7c", "output": "\u4e00\u4e2a"}, {"input": "\u5730\u7403", "output": "\u5927\u53f7"}, {"input": "\u82a5\u672b", "output": "\u5728"}, {"input": "\u5c0f\u7684", "output": "\u7c73"}, {"input": "\u5e7c\u7a1a\u7684", "output": "\u4e00\u4e2a"}, {"input": "\u6d77\u9a6c", "output": "\u548c"}, {"input": "\u9524", "output": "\u4e00\u4e2a"}, {"input": "\u76f8\u673a", "output": "\u4e00\u4e2a"}, {"input": "\u9752\u86d9", "output": "R"}, {"input": "\u51fa\u53bb", "output": "\u5728"}, {"input": "\u9884\u6d4b", "output": "R"}, {"input": "\u52e4\u594b", "output": "\u6211"}, {"input": "\u6709\u6d1e\u5bdf\u529b", "output": "\u5426"}, {"input": "\u8ff7\u4eba\u7684", "output": "\u8fd9"}, {"input": "\u76f4\u5230", "output": "\u5426"}, {"input": "\u5b89\u8be6", "output": "\u548c"}, {"input": "\u5173\u4e8e", "output": "\u548c"}, {"input": "\u8461\u8404", "output": "R"}, {"input": "\u6930\u5b50", "output": "\u8fd9"}, {"input": "\u877e\u8788", "output": "\u548c"}, {"input": "\u78c1\u5e26", "output": "\u4e00\u4e2a"}, {"input": "\u725b\u6cb9\u679c", "output": "V"}, {"input": "\u5fd7\u613f\u8005", "output": "\u8fd9"}, {"input": "\u5c48\u670d", "output": "\u6211"}, {"input": "\u6e29\u548c\u7684", "output": "\u6211"}, {"input": "\u503c\u5f97\u4fe1\u8d56", "output": "R"}, {"input": "\u4e3e\u8d77", "output": "\u6211"}, {"input": "\u72d0\u72f8", "output": "\u8fd9"}, {"input": "\u98df\u8681\u517d", "output": "\u5426"}, {"input": "\u68d5\u8272\u7684", "output": "R"}, {"input": "\u732a\u8089", "output": "\u8fd9"}, {"input": "\u72ee\u5b50", "output": "\u6211"}, {"input": "\u888b\u718a", "output": "\u8fd9"}, {"input": "\u70b9\u71c3", "output": "\u6211"}, {"input": "\u8bb0\u4f4f", "output": "\u548c"}, {"input": "\u65e0\u6240\u754f\u60e7", "output": "\u548c"}, {"input": "\u4e0b\u9762", "output": "\u548c"}, {"input": "Python", "output": "\u548c"}, {"input": "\u6068", "output": "\u4e00\u4e2a"}, {"input": "\u874e", "output": "\u78b3"}, {"input": "\u6162\u7684", "output": "\u5927\u53f7"}, {"input": "\u8349\u8393", "output": "\u7535\u89c6"}, {"input": "\u54a8\u8be2", "output": "\u8fd9"}, {"input": "\u5c0f\u5730\u6bef", "output": "\u5728"}, {"input": "\u7ed3", "output": "\u5426"}, {"input": "\u94f6", "output": "\u6211"}, {"input": "\u5bfc\u822a", "output": "\u4e00\u4e2a"}, {"input": "\u8336\u58f6", "output": "\u548c"}, {"input": "\u674f", "output": "\u78f7"}, {"input": "\u8d70", "output": "\u4e00\u4e2a"}, {"input": "\u4e66", "output": "\u8fd9"}, {"input": "\u6843", "output": "\u548c"}, {"input": "\u7cbe\u5f69\u7684", "output": "\u8fd9"}, {"input": "\u8725\u8734", "output": "\u6211"}, {"input": "\u7d2b\u8272\u7684", "output": "\u5728"}, {"input": "\u9e7f", "output": "\u548c"}, {"input": "\u7406\u60f3\u4e3b\u4e49", "output": "\u5fb7"}, {"input": "\u5e86\u795d", "output": "\u548c"}, {"input": "\u5de5\u4f5c", "output": "\u8fd9"}, {"input": "\u53e3\u9999\u7cd6\u7403", "output": "\u5728"}, {"input": "\u7b14", "output": "\u548c"}, {"input": "\u67e0\u6aac", "output": "\u548c"}, {"input": "\u6d0b\u8471", "output": "\u5426"}, {"input": "\u7b8d", "output": "\u8fd9"}, {"input": "\u86cb\u7cd5", "output": "\u4e00\u4e2a"}, {"input": "\u718a", "output": "\u548c"}, {"input": "\u9664\u4e86", "output": "\u5341"}, {"input": "\u548c", "output": "\u6211"}, {"input": "\u98a0\u7c38", "output": "\u8fd9"}, {"input": "\u8584\u7684", "output": "\u8d6b"}, {"input": "\u751c\u7684", "output": "\u5728"}, {"input": "\u7f51", "output": "\u548c"}, {"input": "\u7edf\u6cbb\u8005", "output": "\u5728"}, {"input": "\u63aa\u65bd", "output": "\u548c"}, {"input": "\u9999\u8549", "output": "\u4e00\u4e2a"}, {"input": "\u7a7f\u8fc7", "output": "\u78b3"}, {"input": "\u5e78\u798f\u7684", "output": "\u5927\u53f7"}, {"input": "\u62a5\u7eb8", "output": "\u548c"}, {"input": "\u5192\u9669", "output": "\u5fb7"}, {"input": "\u8c26\u865a\u7684", "output": "\u8fd9"}, {"input": "\u5fe0\u8bda", "output": "\u548c"}, {"input": "\u8239", "output": "\u8fd9"}, {"input": "\u5584\u826f", "output": "\u6211"}, {"input": "\u753b", "output": "\u4e00\u4e2a"}, {"input": "\u8033\u73af", "output": "\u4e00\u4e2a"}, {"input": "\u53d1\u5c04", "output": "\u4e00\u4e2a"}, {"input": "\u53cd\u5bf9", "output": "\u683c"}, {"input": "\u65e0\u5fe7\u65e0\u8651\u7684", "output": "\u5927\u53f7"}, {"input": "\u8033\u5957", "output": "\u4e00\u4e2a"}, {"input": "\u6ecb\u517b", "output": "\u8fd9"}, {"input": "\u65e5\u7a0b", "output": "\u78b3"}, {"input": "\u4e30\u5bcc", "output": "\u8fd9"}, {"input": "\u8be2\u95ee", "output": "\u5728"}, {"input": "\u7070\u8272\u7684", "output": "R"}, {"input": "\u8c26\u900a\u7684", "output": "\u5728"}, {"input": "\u53d1\u73b0", "output": "\u6211"}, {"input": "\u771f\u8bda", "output": "\u6211"}, {"input": "\u9e58", "output": "\u4e00\u4e2a"}, {"input": "\u6d77\u72f8", "output": "\u548c"}, {"input": "\u4f5c\u4e3a", "output": "\u5e74\u4ee3"}, {"input": "\u70ed\u60c5\u7684", "output": "\u548c"}, {"input": "\u70ed\u5fc3", "output": "\u548c"}, {"input": "\u597d\u5947", "output": "\u5426"}, {"input": "\u9178\u7684", "output": "\u8fd9"}, {"input": "\u94c5\u7b14", "output": "\u548c"}, {"input": "\u8bb2\u8bdd", "output": "\u4e00\u4e2a"}, {"input": "\u5728", "output": "\u5426"}, {"input": "\u543b", "output": "\u6211"}, {"input": "\u51b0", "output": "\u78b3"}, {"input": "\u72ec\u89d2\u9cb8", "output": "\u4e00\u4e2a"}, {"input": "\u5408\u5e76", "output": "\u548c"}, {"input": "\u6c34\u725b", "output": "\u5728"}, {"input": "\u7f8e\u6d32\u864e", "output": "\u4e00\u4e2a"}, {"input": "\u6536\u96c6", "output": "\u4e00\u4e2a"}, {"input": "\u706f", "output": "\u4e00\u4e2a"}, {"input": "\u632f\u594b\u4eba\u5fc3", "output": "\u78f7"}, {"input": "\u5bd2\u51b7\u7684", "output": "\u8fd9"}, {"input": "\u673a\u5668\u4eba", "output": "\u8fd9"}, {"input": "\u4fcf\u76ae\u7684", "output": "\u5927\u53f7"}, {"input": "\u575a\u51b3", "output": "\u548c"}, {"input": "\u6279\u51c6", "output": "\u78f7"}, {"input": "\u5bf9\u5f85", "output": "R"}, {"input": "\u60ca\u4eba\u7684", "output": "\u7c73"}, {"input": "\u91d1\u6a58", "output": "\u5728"}, {"input": "\u4ee4\u4eba\u773c\u82b1\u7f2d\u4e71", "output": "\u4e00\u4e2a"}, {"input": "\u56f4\u88d9", "output": "\u78f7"}, {"input": "\u5728\u4e0b\u9762", "output": "\u5426"}, {"input": "\u4e4b\u4e0a", "output": "\u78f7"}, {"input": "\u706b\u70c8\u9e1f", "output": "\u5927\u53f7"}, {"input": "\u8f66", "output": "\u4e00\u4e2a"}, {"input": "\u548c\u5e73", "output": "\u548c"}, {"input": "\u51b0\u978b", "output": "\u94be"}, {"input": "\u72d7", "output": "\u8fd9"}, {"input": "\u6cbf\u7740", "output": "\u5927\u53f7"}, {"input": "\u6d77\u519b", "output": "\u4e00\u4e2a"}, {"input": "\u732b\u5934\u9e70", "output": "\u5728"}, {"input": "\u6a59\u5b50", "output": "R"}, {"input": "\u676f\u5b50", "output": "\u5728"}, {"input": "\u94b1\u5305", "output": "\u4e00\u4e2a"}, {"input": "\u9ed1\u6697\u7684", "output": "\u4e00\u4e2a"}, {"input": "\u6b22\u4e50", "output": "\u8fd9"}, {"input": "\u7a97\u5e18", "output": "\u5728"}, {"input": "\u83e0\u841d\u871c", "output": "\u4e00\u4e2a"}, {"input": "\u611f\u6fc0\u7684", "output": "R"}, {"input": "\u591a\u624d\u591a\u827a\u7684", "output": "\u548c"}, {"input": "\u5199", "output": "R"}, {"input": "\u9e21", "output": "\u8d6b"}, {"input": "\u5e72\u71e5", "output": "R"}, {"input": "\u77ed\u5c3e\u77ee\u888b\u9f20", "output": "\u5728"}, {"input": "\u96c0\u79d1", "output": "\u6211"}, {"input": "\u725b\u4ed4\u88e4", "output": "\u548c"}]